HISTORY.rst
LICENSE.rst
MANIFEST.in
README.rst
requirements.txt
requirements_dev.txt
requirements_test.txt
setup.cfg
setup.py
daf/__init__.py
daf/groups.py
daf.egg-info/PKG-INFO
daf.egg-info/SOURCES.txt
daf.egg-info/dependency_links.txt
daf.egg-info/requires.txt
daf.egg-info/top_level.txt
daf/access/__init__.py
daf/access/operations.py
daf/access/readers.py
daf/access/writers.py
daf/storage/__init__.py
daf/storage/anndata.py
daf/storage/chains.py
daf/storage/files.py
daf/storage/h5fs.py
daf/storage/interface.py
daf/storage/memory.py
daf/storage/memory_mapping.py
daf/storage/none.py
daf/storage/views.py
daf/typing/__init__.py
daf/typing/dense.py
daf/typing/descriptions.py
daf/typing/dtypes.py
daf/typing/fake_pandas.py
daf/typing/fake_sparse.py
daf/typing/frames.py
daf/typing/freezing.py
daf/typing/layouts.py
daf/typing/matrices.py
daf/typing/optimization.py
daf/typing/series.py
daf/typing/sparse.py
daf/typing/unions.py
daf/typing/vectors.py
tests/__init__.py
tests/test_access.py
tests/test_anndata.py
tests/test_chain.py
tests/test_dense.py
tests/test_disk.py
tests/test_dtypes.py
tests/test_frames.py
tests/test_freezing.py
tests/test_groups.py
tests/test_layouts.py
tests/test_memory.py
tests/test_memory_mapping.py
tests/test_operations.py
tests/test_optimization.py
tests/test_series.py
tests/test_sparse.py
tests/test_vectors.py
tests/test_views.py