Metadata-Version: 2.1
Name: daf
Version: 0.1.0
Summary: Data in Axes in Formats
Home-page: https://github.com/tanaylab/daf.git
Author: Oren Ben-Kiki
Author-email: oren@ben-kiki.org
License: MIT license
Keywords: daf
Platform: UNKNOWN
Classifier: Development Status :: 3 - Alpha
Classifier: Intended Audience :: Developers
Classifier: Natural Language :: English
Classifier: Programming Language :: Python :: 3
Classifier: Programming Language :: Python :: 3.7
Classifier: Programming Language :: Python :: 3.8
Classifier: Programming Language :: Python :: 3.9
Classifier: Programming Language :: Python :: 3.10
Classifier: Topic :: Software Development :: Libraries
Classifier: Topic :: Scientific/Engineering :: Bio-Informatics
Classifier: Intended Audience :: Developers
Classifier: Intended Audience :: Science/Research
Requires-Python: >=3.7
Provides-Extra: dev
License-File: LICENSE.rst
